fast_encrypt/__init__.py
fast_encrypt/_atbash.py
fast_encrypt/_caesars_cipher.py
fast_encrypt/_homophonic_substitution.py
fast_encrypt/_morse_code.py
fast_encrypt/_pipeline.py
fast_encrypt/_rsa.py
fast_encrypt/_simple_encryptor.py
fast_encrypt/_substitution.py
fast_encrypt/_vigenere.py
fast_encrypt-1.0.0.dist-info/LICENSE.md
fast_encrypt-1.0.0.dist-info/METADATA
fast_encrypt-1.0.0.dist-info/WHEEL
fast_encrypt-1.0.0.dist-info/top_level.txt
fast_encrypt-1.0.0.dist-info/RECORD
